keptcha/__init__.py
keptcha/async_captcha.py
keptcha/base.py
keptcha/captcha.py
keptcha/errors.py
keptcha-0.1.2.dist-info/LICENSE
keptcha-0.1.2.dist-info/METADATA
keptcha-0.1.2.dist-info/WHEEL
keptcha-0.1.2.dist-info/top_level.txt
keptcha-0.1.2.dist-info/RECORD
