Metadata-Version: 2.1
Name: keptcha
Version: 0.1.2
Summary: keptcha is an API wrapper for https://captcha-api.akshit.me written in Python.
Home-page: https://github.com/captcha-api/keptcha-py
Author: Syed_Ahkam
Author-email: smahkam313@gmail.com
License: UNKNOWN
Project-URL: Website, https://captcha-api.akshit.me
Project-URL: Source, https://github.com/captcha-api/keptcha-py
Keywords: captcha,api,wrapper,async
Platform: UNKNOWN
Classifier: Development Status :: 3 - Alpha
Classifier: Intended Audience :: Developers
Classifier: Topic :: Internet
Classifier: Topic :: Software Development :: Libraries
Classifier: Topic :: Software Development :: Libraries :: Python Modules
Classifier: Natural Language :: English
Classifier: License :: OSI Approved :: MIT License
Classifier: Operating System :: OS Independent
Classifier: Programming Language :: Python :: 3.6
Classifier: Programming Language :: Python :: 3.7
Classifier: Programming Language :: Python :: 3.8
Classifier: Programming Language :: Python :: 3.9
Requires-Python: >=3.6
License-File: LICENSE
